setup.cfg
setup.py
flapjacks/__init__.py
flapjacks/settings.py
flapjacks/urls.py
flapjacks/wsgi.py
flapjacks.egg-info/PKG-INFO
flapjacks.egg-info/SOURCES.txt
flapjacks.egg-info/dependency_links.txt
flapjacks.egg-info/top_level.txt