Metadata-Version: 1.1
Name: flapjacks
Version: 0.1.0
Summary: A Python project for transcoding videos on AWS and deploying them to Youtube.
Home-page: https://github.com/ahmedaljazzar/flapjacks
Author: Ahmed Jazzar
Author-email: me@ahmedjazzar.com
License: MIT License
Platform: UNKNOWN
Classifier: Development Status :: 1 - Planning
Classifier: Intended Audience :: Developers
Classifier: Operating System :: OS Independent
Classifier: Programming Language :: Python
